jupyterlab_hidecell/__init__.py
jupyterlab_hidecell/_version.py
jupyterlab_hidecell/hideinput_to_hidecell.py
jupyterlab_hidecell-0.2.2.data/data/share/jupyter/labextensions/jupyterlab-hidecell/package.json
jupyterlab_hidecell-0.2.2.data/data/share/jupyter/labextensions/jupyterlab-hidecell/schemas/jupyterlab-hidecell/package.json.orig
jupyterlab_hidecell-0.2.2.data/data/share/jupyter/labextensions/jupyterlab-hidecell/schemas/jupyterlab-hidecell/plugin.json
jupyterlab_hidecell-0.2.2.data/data/share/jupyter/labextensions/jupyterlab-hidecell/static/568.2004c6355d0f680f812b.js
jupyterlab_hidecell-0.2.2.data/data/share/jupyter/labextensions/jupyterlab-hidecell/static/747.fb5c13b5fdf1cd1dda5e.js
jupyterlab_hidecell-0.2.2.data/data/share/jupyter/labextensions/jupyterlab-hidecell/static/793.9bb976cb665434175ee3.js
jupyterlab_hidecell-0.2.2.data/data/share/jupyter/labextensions/jupyterlab-hidecell/static/remoteEntry.2a8cbd937615452ac0b1.js
jupyterlab_hidecell-0.2.2.data/data/share/jupyter/labextensions/jupyterlab-hidecell/static/style.js
jupyterlab_hidecell-0.2.2.data/data/share/jupyter/labextensions/jupyterlab-hidecell/static/third-party-licenses.json
jupyterlab_hidecell-0.2.2.data/data/share/jupyter/labextensions/jupyterlab-hidecell/install.json
jupyterlab_hidecell-0.2.2.dist-info/METADATA
jupyterlab_hidecell-0.2.2.dist-info/WHEEL
jupyterlab_hidecell-0.2.2.dist-info/entry_points.txt
jupyterlab_hidecell-0.2.2.dist-info/licenses/LICENSE
jupyterlab_hidecell-0.2.2.dist-info/RECORD
