Metadata-Version: 2.1
Name: jupyterlab_hidecell
Version: 0.2.2
Summary: Jlab extension for showing course levels and structure
Project-URL: Homepage, https://github.com/parmentelat/jupyterlab-hidecell
Project-URL: Bug Tracker, https://github.com/parmentelat/jupyterlab-hidecell/issues
Project-URL: Repository, https://github.com/parmentelat/jupyterlab-hidecell.git
Author-email: Thierry Parmentelat <thierry.parmentelat@inria.fr>
License: BSD 3-Clause License
License-File: LICENSE
Classifier: Framework :: Jupyter :: JupyterLab :: Extensions :: Prebuilt
Classifier: License :: OSI Approved :: BSD License
Classifier: Programming Language :: Python :: 3
Requires-Python: >=3.8
Requires-Dist: jupyterlab-celltagsclasses
